huynhminhkhoi/__init__.py
huynhminhkhoi/admin.py
huynhminhkhoi-0.5.0.dist-info/LICENSE
huynhminhkhoi-0.5.0.dist-info/METADATA
huynhminhkhoi-0.5.0.dist-info/WHEEL
huynhminhkhoi-0.5.0.dist-info/top_level.txt
huynhminhkhoi-0.5.0.dist-info/RECORD
