Metadata-Version: 2.1
Name: huynhminhkhoi
Version: 0.5.0
Summary: Né Bug Nhẹ
Author-email: Huỳnh Minh Khôi <prokunkhoi@gmail.com>
Project-URL: Homepage, https://github.com/huynhminhkhoi888/KhoiHuynhSenpai
Project-URL: Issues, https://github.com/huynhminhkhoi888/KhoiHuynhSenpai
Classifier: Programming Language :: Python :: 3
Classifier: License :: OSI Approved :: MIT License
Classifier: Operating System :: OS Independent
Requires-Python: >=3.8
License-File: LICENSE
